bees_algorithm/__init__.py
bees_algorithm/bees_algorithm.py
bees_algorithm/bees_algorithm_parallel_algorithm.py
bees_algorithm/bees_algorithm_parallel_testing.py
bees_algorithm-1.0.2.dist-info/LICENSE
bees_algorithm-1.0.2.dist-info/METADATA
bees_algorithm-1.0.2.dist-info/WHEEL
bees_algorithm-1.0.2.dist-info/top_level.txt
bees_algorithm-1.0.2.dist-info/RECORD
