Metadata-Version: 2.1
Name: bees_algorithm
Version: 1.0.2
Summary: A Python implementation of the Bees Algorithm. This library allows an out-of-the-box use of the optimisation algorithm on an user-defined target function. The algorithm can be configured to find either the minimum or the maximum of the target function with an iterative process.
Home-page: https://gitlab.com/bees-algorithm/bees_algorithm_python
Author: Luca Baronti
Author-email: lbaronti@gmail.com
License: GNUv3
Download-URL: https://pypi.org/project/bees_algorithm/
Keywords: Optimisation,Optimization,Bees Algorithm,Intelligent Optimisation
Platform: UNKNOWN
Classifier: Development Status :: 5 - Production/Stable
Classifier: Intended Audience :: Education
Classifier: Intended Audience :: Science/Research
Classifier: Topic :: Scientific/Engineering :: Mathematics
Classifier: License :: OSI Approved :: GNU General Public License v3 (GPLv3)
Classifier: Programming Language :: Python :: 3
License-File: LICENSE
